MANIFEST.in
README.md
setup.py
sentry_irc/__init__.py
sentry_irc/plugin.py
sentry_irc/tests.py
sentry_irc.egg-info/PKG-INFO
sentry_irc.egg-info/SOURCES.txt
sentry_irc.egg-info/dependency_links.txt
sentry_irc.egg-info/entry_points.txt
sentry_irc.egg-info/not-zip-safe
sentry_irc.egg-info/requires.txt
sentry_irc.egg-info/top_level.txt