Metadata-Version: 1.0
Name: sentry-irc
Version: 3.0.0
Summary: A Sentry extension which integrates with IRC
Home-page: http://code.gisce.net/sentry-irc
Author: Eduard Carreras
Author-email: ecarreras@gisce.net
License: BSD
Platform: UNKNOWN
Classifier: Framework :: Django
Classifier: Intended Audience :: Developers
Classifier: Intended Audience :: System Administrators
Classifier: Operating System :: OS Independent
Classifier: Topic :: Software Development
